{
    "00" : ["nop"],
    "01" : ["aconst_null"],
    "02" : ["iconst_m1"],
    "03" : ["iconst_0"],
    "04" : ["iconst_1"],
    "05" : ["iconst_2"],
    "06" : ["iconst_3"],
    "07" : ["iconst_4"],
    "08" : ["iconst_5"],
    "09" : ["lconst_0"],
    "0A" : ["lconst_1"],
    "0B" : ["fconst_0"],
    "0C" : ["fconst_1"],
    "0D" : ["fconst_2"],
    "0E" : ["dconst_0"],
    "0F" : ["dconst_1"],
    "10" : ["bipush",2],
    "11" : ["sipush",2],
    "12" : ["ldc",2],
    "13" : ["ldc_w",2],
    "14" : ["ldc2_w",2],
    "15" : ["iload",4],
    "16" : ["lload",8],
    "17" : ["fload",4],
    "18" : ["dload",8],
    "19" : ["aload",1],
    "1A" : ["iload_0"],
    "1B" : ["iload_1"],
    "1C" : ["iload_2"],
    "1D" : ["iload_3"],
    "1E" : ["lload_0"],
    "1F" : ["lload_1"],
    "20" : ["lload_2"],
    "21" : ["lload_3"],
    "22" : ["fload_0"],
    "23" : ["fload_1"],
    "24" : ["fload_2"],
    "25" : ["fload_3"],
    "26" : ["dload_0"],
    "27" : ["dload_1"],
    "28" : ["dload_2"],
    "29" : ["dload_3"],
    "2A" : ["aload_0"],
    "2B" : ["aload_1"],
    "2C" : ["aload_2"],
    "2D" : ["aload_3"],
    "2E" : ["iaload"],
    "2F" : ["laload"],
    "30" : ["faload"],
    "31" : ["daload"],
    "32" : ["aaload"],
    "33" : ["baload"],
    "34" : ["caload"],
    "35" : ["saload"],
    "36" : ["istore",1],
    "37" : ["lstore",1],
    "38" : ["fstore",1],
    "39" : ["dstore",1],
    "3A" : ["astore",1],
    "3B" : ["istore_0"],
    "3C" : ["istore_1"],
    "3D" : ["istore_2"],
    "3E" : ["istore_3"],
    "3F" : ["lstore_0"],
    "40" : ["lstore_1"],
    "41" : ["lstore_2"],
    "42" : ["lstore_3"],
    "43" : ["fstore_0"],
    "44" : ["fstore_1"],
    "45" : ["fstore_2"],
    "46" : ["fstore_3"],
    "47" : ["dstore_0"],
    "48" : ["dstore_1"],
    "49" : ["dstore_2"],
    "4A" : ["dstore_3"],
    "4B" : ["astore_0"],
    "4C" : ["astore_1"],
    "4D" : ["astore_2"],
    "4E" : ["astore_3"],
    "4F" : ["iastore"],
    "50" : ["lastore"],
    "51" : ["fastore"],
    "52" : ["dastore"],
    "53" : ["aastore"],
    "54" : ["bastore"],
    "55" : ["castore"],
    "56" : ["sastore"],
    "57" : ["pop"],
    "58" : ["pop2"],
    "59" : ["dup"],
    "5A" : ["dup_x1"],
    "5B" : ["dup_x2"],
    "5C" : ["dup2"],
    "5D" : ["dup2_x1"],
    "5E" : ["dup2_x2"],
    "5F" : ["swap"],
    "60" : ["iadd"],
    "61" : ["ladd"],
    "62" : ["fadd"],
    "63" : ["dadd"],
    "64" : ["isub"],
    "65" : ["lsub"],
    "66" : ["fsub"],
    "67" : ["dsub"],
    "68" : ["imul"],
    "69" : ["lmul"],
    "6A" : ["fmul"],
    "6B" : ["dmul"],
    "6C" : ["idiv"],
    "6D" : ["ldiv"],
    "6E" : ["fdiv"],
    "6F" : ["ddiv"],
    "70" : ["irem"],
    "71" : ["lrem"],
    "72" : ["frem"],
    "73" : ["drem"],
    "74" : ["ineg"],
    "75" : ["lneg"],
    "76" : ["fneg"],
    "77" : ["dneg"],
    "78" : ["ishl"],
    "79" : ["lshl"],
    "7A" : ["ishr"],
    "7B" : ["lshr"],
    "7C" : ["iushr"],
    "7D" : ["lushr"],
    "7E" : ["iand"],
    "7F" : ["land"],
    "80" : ["ior"],
    "81" : ["lor"],
    "82" : ["ixor"],
    "83" : ["lxor"],
    "84" : ["iinc"],
    "85" : ["i2l"],
    "86" : ["i2f"],
    "87" : ["i2d"],
    "88" : ["l2i"],
    "89" : ["l2f"],
    "8A" : ["l2d"],
    "8B" : ["f2i"],
    "8C" : ["f2l"],
    "8D" : ["f2d"],
    "8E" : ["d2i"],
    "8F" : ["d2l"],
    "90" : ["d2f"],
    "91" : ["i2b"],
    "92" : ["i2c"],
    "93" : ["i2s"],
    "94" : ["lcmp"],
    "95" : ["fcmpl"],
    "96" : ["fcmpg"],
    "97" : ["dcmpl"],
    "98" : ["dcmpg"],
    "99" : ["ifeq",2],
    "9A" : ["ifne",2],
    "9B" : ["iflt",2],
    "9C" : ["ifge",2],
    "9D" : ["ifgt",2],
    "9E" : ["ifle",2],
    "9F" : ["if_icmpeq",2],
    "A0" : ["if_icmpne",2],
    "A1" : ["if_icmplt",2],
    "A2" : ["if_icmpge",2],
    "A3" : ["if_icmpgt",2],
    "A4" : ["if_icmple",2],
    "A5" : ["if_acmpeq",2],
    "A6" : ["if_acmpne",2],
    "A7" : ["goto",2],
    "A8" : ["jsr",2],
    "A9" : ["ret",2],
    "AA" : ["tableswitch"],
    "AB" : ["lookupswitch"],
    "AC" : ["ireturn"],
    "AD" : ["lreturn"],
    "AE" : ["freturn"],
    "AF" : ["dreturn"],
    "B0" : ["areturn"],
    "B1" : ["return"],
    "B2" : ["getstatic",2],
    "B3" : ["putstatic",2],
    "B4" : ["getfield",2],
    "B5" : ["putfield",2],
    "B6" : ["invokevirtual",2],
    "B7" : ["invokespecial",2],
    "B8" : ["invokestatic",2],
    "b9" : ["invokeinterface",2],
    "BA" : ["---"],
    "BB" : ["new"],
    "BC" : ["newarray"],
    "BD" : ["anewarray"],
    "BE" : ["arraylength"],
    "BF" : ["athrow"],
    "C0" : ["checkcast",2],
    "c1" : ["instanceof",2],
    "C2" : ["monitorenter"],
    "C3" : ["monitorexit"],
    "C4" : ["wide"],
    "C5" : ["multianewarray"],
    "C6" : ["ifnull",2],
    "C7" : ["ifnonnull",2],
    "C8" : ["goto_w",4],
    "C9" : ["jsr_w",4],
    "CA" : ["breakpoint"],
    "FE" : ["impdep1"],
    "FF" : ["impdep2"]
}
